{"ndcg_at_1": 0.35375, "ndcg_at_3": 0.41436, "ndcg_at_5": 0.42724, "ndcg_at_10": 0.45354, "ndcg_at_20": 0.4771, "ndcg_at_100": 0.51278, "ndcg_at_200": 0.52375, "ndcg_at_300": 0.52655, "ndcg_at_500": 0.53021, "ndcg_at_1000": 0.53449, "map_at_1": 0.30196, "map_at_3": 0.37182, "map_at_5": 0.38319, "map_at_10": 0.39705, "map_at_20": 0.40702, "map_at_100": 0.41452, "map_at_200": 0.41574, "map_at_300": 0.41611, "map_at_500": 0.41645, "map_at_1000": 0.41672, "recall_at_1": 0.30196, "recall_at_3": 0.44104, "recall_at_5": 0.47817, "recall_at_10": 0.55509, "recall_at_20": 0.64027, "recall_at_100": 0.81857, "recall_at_200": 0.88272, "recall_at_300": 0.89697, "recall_at_500": 0.91856, "recall_at_1000": 0.94716, "precision_at_1": 0.35375, "precision_at_3": 0.19302, "precision_at_5": 0.13162, "precision_at_10": 0.08399, "precision_at_20": 0.05375, "precision_at_100": 0.01632, "precision_at_200": 0.00965, "precision_at_300": 0.00694, "precision_at_500": 0.00455, "precision_at_1000": 0.0025, "mrr_at_1": 0.35375, "mrr_at_3": 0.42325, "mrr_at_5": 0.43274, "mrr_at_10": 0.44293, "mrr_at_20": 0.44849, "mrr_at_100": 0.45216, "mrr_at_200": 0.45252, "mrr_at_300": 0.45255, "mrr_at_500": 0.45259, "mrr_at_1000": 0.45261, "rc_at_1": {"relevant": 0.0, "distractor": 0.0}, "rc_at_3": {"relevant": 0.0, "distractor": 0.0}, "rc_at_5": {"relevant": 0.0, "distractor": 0.0}, "rc_at_10": {"relevant": 0.0, "distractor": 0.0}, "rc_at_20": {"relevant": 0.0, "distractor": 0.0}, "rc_at_100": {"relevant": 0.0, "distractor": 0.0}, "rc_at_200": {"relevant": 0.0, "distractor": 0.0}, "rc_at_300": {"relevant": 0.0, "distractor": 0.0}, "rc_at_500": {"relevant": 0.0, "distractor": 0.0}, "rc_at_1000": {"relevant": 0.0, "distractor": 0.0}}