{"ndcg_at_1": 0.188, "ndcg_at_3": 0.14339, "ndcg_at_5": 0.12356, "ndcg_at_10": 0.14679, "ndcg_at_20": 0.16636, "ndcg_at_100": 0.20744, "ndcg_at_200": 0.22026, "ndcg_at_300": 0.22921, "ndcg_at_500": 0.23902, "ndcg_at_1000": 0.25254, "map_at_1": 0.03843, "map_at_3": 0.0641, "map_at_5": 0.07448, "map_at_10": 0.08519, "map_at_20": 0.0915, "map_at_100": 0.09857, "map_at_200": 0.09954, "map_at_300": 0.09999, "map_at_500": 0.10033, "map_at_1000": 0.10066, "recall_at_1": 0.03843, "recall_at_3": 0.08022, "recall_at_5": 0.10732, "recall_at_10": 0.14977, "recall_at_20": 0.19605, "recall_at_100": 0.33057, "recall_at_200": 0.3852, "recall_at_300": 0.42737, "recall_at_500": 0.47752, "recall_at_1000": 0.55338, "precision_at_1": 0.188, "precision_at_3": 0.131, "precision_at_5": 0.1052, "precision_at_10": 0.0736, "precision_at_20": 0.0482, "precision_at_100": 0.01627, "precision_at_200": 0.00947, "precision_at_300": 0.00701, "precision_at_500": 0.0047, "precision_at_1000": 0.00272, "mrr_at_1": 0.188, "mrr_at_3": 0.24067, "mrr_at_5": 0.25587, "mrr_at_10": 0.26871, "mrr_at_20": 0.27466, "mrr_at_100": 0.27958, "mrr_at_200": 0.27993, "mrr_at_300": 0.28009, "mrr_at_500": 0.28022, "mrr_at_1000": 0.28027, "rc_at_1": {"relevant": 0.0, "distractor": 0.0}, "rc_at_3": {"relevant": 0.0, "distractor": 0.0}, "rc_at_5": {"relevant": 0.0, "distractor": 0.0}, "rc_at_10": {"relevant": 0.0, "distractor": 0.0}, "rc_at_20": {"relevant": 0.0, "distractor": 0.0}, "rc_at_100": {"relevant": 0.0, "distractor": 0.0}, "rc_at_200": {"relevant": 0.0, "distractor": 0.0}, "rc_at_300": {"relevant": 0.0, "distractor": 0.0}, "rc_at_500": {"relevant": 0.0, "distractor": 0.0}, "rc_at_1000": {"relevant": 0.0, "distractor": 0.0}}