{"ndcg_at_1": 0.0, "ndcg_at_3": 0.24553, "ndcg_at_5": 0.31327, "ndcg_at_10": 0.37487, "ndcg_at_20": 0.40616, "ndcg_at_100": 0.42156, "ndcg_at_200": 0.42338, "ndcg_at_300": 0.42383, "ndcg_at_500": 0.42407, "ndcg_at_1000": 0.42453, "map_at_1": 0.0, "map_at_3": 0.18599, "map_at_5": 0.22361, "map_at_10": 0.24915, "map_at_20": 0.25792, "map_at_100": 0.2603, "map_at_200": 0.2604, "map_at_300": 0.26042, "map_at_500": 0.26042, "map_at_1000": 0.26043, "recall_at_1": 0.0, "recall_at_3": 0.4175, "recall_at_5": 0.58179, "recall_at_10": 0.77169, "recall_at_20": 0.89403, "recall_at_100": 0.97368, "recall_at_200": 0.98649, "recall_at_300": 0.99004, "recall_at_500": 0.99218, "recall_at_1000": 0.99644, "precision_at_1": 0.0, "precision_at_3": 0.13917, "precision_at_5": 0.11636, "precision_at_10": 0.07717, "precision_at_20": 0.0447, "precision_at_100": 0.00974, "precision_at_200": 0.00493, "precision_at_300": 0.0033, "precision_at_500": 0.00198, "precision_at_1000": 0.001, "mrr_at_1": 0.0, "mrr_at_3": 0.18575, "mrr_at_5": 0.22359, "mrr_at_10": 0.24913, "mrr_at_20": 0.25789, "mrr_at_100": 0.26028, "mrr_at_200": 0.26037, "mrr_at_300": 0.26039, "mrr_at_500": 0.2604, "mrr_at_1000": 0.2604, "rc_at_1": {"relevant": 0.0, "distractor": 0.0}, "rc_at_3": {"relevant": 0.0, "distractor": 0.0}, "rc_at_5": {"relevant": 0.0, "distractor": 0.0}, "rc_at_10": {"relevant": 0.0, "distractor": 0.0}, "rc_at_20": {"relevant": 0.0, "distractor": 0.0}, "rc_at_100": {"relevant": 0.0, "distractor": 0.0}, "rc_at_200": {"relevant": 0.0, "distractor": 0.0}, "rc_at_300": {"relevant": 0.0, "distractor": 0.0}, "rc_at_500": {"relevant": 0.0, "distractor": 0.0}, "rc_at_1000": {"relevant": 0.0, "distractor": 0.0}}