{"ndcg_at_1": 0.50784, "ndcg_at_3": 0.57422, "ndcg_at_5": 0.60253, "ndcg_at_10": 0.62386, "ndcg_at_20": 0.64282, "ndcg_at_100": 0.66332, "ndcg_at_200": 0.66733, "ndcg_at_300": 0.66892, "ndcg_at_500": 0.67057, "ndcg_at_1000": 0.67218, "map_at_1": 0.44629, "map_at_3": 0.53773, "map_at_5": 0.55766, "map_at_10": 0.56954, "map_at_20": 0.57624, "map_at_100": 0.57988, "map_at_200": 0.58019, "map_at_300": 0.58027, "map_at_500": 0.58032, "map_at_1000": 0.58035, "recall_at_1": 0.44629, "recall_at_3": 0.61949, "recall_at_5": 0.68805, "recall_at_10": 0.74774, "recall_at_20": 0.81759, "recall_at_100": 0.91686, "recall_at_200": 0.94155, "recall_at_300": 0.95194, "recall_at_500": 0.96459, "recall_at_1000": 0.9784, "precision_at_1": 0.50784, "precision_at_3": 0.25266, "precision_at_5": 0.17292, "precision_at_10": 0.09762, "precision_at_20": 0.05455, "precision_at_100": 0.01259, "precision_at_200": 0.00653, "precision_at_300": 0.00444, "precision_at_500": 0.00271, "precision_at_1000": 0.00138, "mrr_at_1": 0.50909, "mrr_at_3": 0.58318, "mrr_at_5": 0.5971, "mrr_at_10": 0.60468, "mrr_at_20": 0.60898, "mrr_at_100": 0.61117, "mrr_at_200": 0.6113, "mrr_at_300": 0.61133, "mrr_at_500": 0.61136, "mrr_at_1000": 0.61138, "rc_at_1": {"relevant": 0.0, "distractor": 0.0}, "rc_at_3": {"relevant": 0.0, "distractor": 0.0}, "rc_at_5": {"relevant": 0.0, "distractor": 0.0}, "rc_at_10": {"relevant": 0.0, "distractor": 0.0}, "rc_at_20": {"relevant": 0.0, "distractor": 0.0}, "rc_at_100": {"relevant": 0.0, "distractor": 0.0}, "rc_at_200": {"relevant": 0.0, "distractor": 0.0}, "rc_at_300": {"relevant": 0.0, "distractor": 0.0}, "rc_at_500": {"relevant": 0.0, "distractor": 0.0}, "rc_at_1000": {"relevant": 0.0, "distractor": 0.0}}