{"ndcg_at_1": 0.33846, "ndcg_at_3": 0.33124, "ndcg_at_5": 0.30719, "ndcg_at_10": 0.2572, "ndcg_at_20": 0.30385, "ndcg_at_100": 0.45717, "ndcg_at_200": 0.50141, "ndcg_at_300": 0.51168, "ndcg_at_500": 0.51912, "ndcg_at_1000": 0.5273, "map_at_1": 0.03385, "map_at_3": 0.08154, "map_at_5": 0.10662, "map_at_10": 0.14429, "map_at_20": 0.16588, "map_at_100": 0.21193, "map_at_200": 0.22042, "map_at_300": 0.22155, "map_at_500": 0.22216, "map_at_1000": 0.22257, "recall_at_1": 0.03385, "recall_at_3": 0.09846, "recall_at_5": 0.14769, "recall_at_10": 0.22923, "recall_at_20": 0.31231, "recall_at_100": 0.70769, "recall_at_200": 0.84923, "recall_at_300": 0.88615, "recall_at_500": 0.91538, "recall_at_1000": 0.95077, "precision_at_1": 0.33846, "precision_at_3": 0.32821, "precision_at_5": 0.29538, "precision_at_10": 0.22923, "precision_at_20": 0.15615, "precision_at_100": 0.07077, "precision_at_200": 0.04246, "precision_at_300": 0.02954, "precision_at_500": 0.01831, "precision_at_1000": 0.00951, "mrr_at_1": 0.33846, "mrr_at_3": 0.44103, "mrr_at_5": 0.47872, "mrr_at_10": 0.4916, "mrr_at_20": 0.49796, "mrr_at_100": 0.50004, "mrr_at_200": 0.50004, "mrr_at_300": 0.50004, "mrr_at_500": 0.50004, "mrr_at_1000": 0.50004, "rc_at_1": {"relevant": 0.33846, "distractor": 0.64615}, "rc_at_3": {"relevant": 0.98462, "distractor": 2.0}, "rc_at_5": {"relevant": 1.47692, "distractor": 3.49231}, "rc_at_10": {"relevant": 2.27692, "distractor": 7.6}, "rc_at_20": {"relevant": 3.13846, "distractor": 16.27692}, "rc_at_100": {"relevant": 7.09231, "distractor": 73.0}, "rc_at_200": {"relevant": 8.49231, "distractor": 87.01538}, "rc_at_300": {"relevant": 8.86154, "distractor": 90.0}, "rc_at_500": {"relevant": 9.15385, "distractor": 92.46154}, "rc_at_1000": {"relevant": 9.52308, "distractor": 94.76923}}