{"ndcg_at_1": 0.0, "ndcg_at_3": 0.31413, "ndcg_at_5": 0.37446, "ndcg_at_10": 0.4346, "ndcg_at_20": 0.45608, "ndcg_at_100": 0.46391, "ndcg_at_200": 0.46471, "ndcg_at_300": 0.46471, "ndcg_at_500": 0.46479, "ndcg_at_1000": 0.46494, "map_at_1": 0.0, "map_at_3": 0.23838, "map_at_5": 0.27185, "map_at_10": 0.29687, "map_at_20": 0.30291, "map_at_100": 0.30415, "map_at_200": 0.3042, "map_at_300": 0.3042, "map_at_500": 0.3042, "map_at_1000": 0.3042, "recall_at_1": 0.0, "recall_at_3": 0.53272, "recall_at_5": 0.67923, "recall_at_10": 0.86415, "recall_at_20": 0.94808, "recall_at_100": 0.98791, "recall_at_200": 0.9936, "recall_at_300": 0.9936, "recall_at_500": 0.99431, "recall_at_1000": 0.99573, "precision_at_1": 0.0, "precision_at_3": 0.17757, "precision_at_5": 0.13585, "precision_at_10": 0.08642, "precision_at_20": 0.0474, "precision_at_100": 0.00988, "precision_at_200": 0.00497, "precision_at_300": 0.00331, "precision_at_500": 0.00199, "precision_at_1000": 0.001, "mrr_at_1": 0.0, "mrr_at_3": 0.23826, "mrr_at_5": 0.27173, "mrr_at_10": 0.29675, "mrr_at_20": 0.30279, "mrr_at_100": 0.30404, "mrr_at_200": 0.30408, "mrr_at_300": 0.30408, "mrr_at_500": 0.30408, "mrr_at_1000": 0.30408, "rc_at_1": {"relevant": 0.0, "distractor": 0.0}, "rc_at_3": {"relevant": 0.0, "distractor": 0.0}, "rc_at_5": {"relevant": 0.0, "distractor": 0.0}, "rc_at_10": {"relevant": 0.0, "distractor": 0.0}, "rc_at_20": {"relevant": 0.0, "distractor": 0.0}, "rc_at_100": {"relevant": 0.0, "distractor": 0.0}, "rc_at_200": {"relevant": 0.0, "distractor": 0.0}, "rc_at_300": {"relevant": 0.0, "distractor": 0.0}, "rc_at_500": {"relevant": 0.0, "distractor": 0.0}, "rc_at_1000": {"relevant": 0.0, "distractor": 0.0}}