{"ndcg_at_1": 0.32308, "ndcg_at_3": 0.23782, "ndcg_at_5": 0.21701, "ndcg_at_10": 0.17968, "ndcg_at_20": 0.21682, "ndcg_at_100": 0.28964, "ndcg_at_200": 0.31571, "ndcg_at_300": 0.33268, "ndcg_at_500": 0.3461, "ndcg_at_1000": 0.36859, "map_at_1": 0.03231, "map_at_3": 0.05359, "map_at_5": 0.06967, "map_at_10": 0.09195, "map_at_20": 0.10858, "map_at_100": 0.12544, "map_at_200": 0.12844, "map_at_300": 0.12975, "map_at_500": 0.13065, "map_at_1000": 0.13162, "recall_at_1": 0.03231, "recall_at_3": 0.06462, "recall_at_5": 0.09692, "recall_at_10": 0.15231, "recall_at_20": 0.22, "recall_at_100": 0.40462, "recall_at_200": 0.48923, "recall_at_300": 0.55077, "recall_at_500": 0.60308, "recall_at_1000": 0.7, "precision_at_1": 0.32308, "precision_at_3": 0.21538, "precision_at_5": 0.19385, "precision_at_10": 0.15231, "precision_at_20": 0.11, "precision_at_100": 0.04046, "precision_at_200": 0.02446, "precision_at_300": 0.01836, "precision_at_500": 0.01206, "precision_at_1000": 0.007, "mrr_at_1": 0.32308, "mrr_at_3": 0.40256, "mrr_at_5": 0.42026, "mrr_at_10": 0.43628, "mrr_at_20": 0.44176, "mrr_at_100": 0.44539, "mrr_at_200": 0.44576, "mrr_at_300": 0.44576, "mrr_at_500": 0.44576, "mrr_at_1000": 0.44576, "rc_at_1": {"relevant": 0.32308, "distractor": 0.61538}, "rc_at_3": {"relevant": 0.67692, "distractor": 2.03077}, "rc_at_5": {"relevant": 1.0, "distractor": 3.38462}, "rc_at_10": {"relevant": 1.56923, "distractor": 6.78462}, "rc_at_20": {"relevant": 2.23077, "distractor": 13.03077}, "rc_at_100": {"relevant": 4.23077, "distractor": 40.58462}, "rc_at_200": {"relevant": 5.10769, "distractor": 51.38462}, "rc_at_300": {"relevant": 5.73846, "distractor": 56.75385}, "rc_at_500": {"relevant": 6.33846, "distractor": 63.87692}, "rc_at_1000": {"relevant": 7.01538, "distractor": 71.04615}}