{"ndcg_at_1": 0.36923, "ndcg_at_3": 0.27942, "ndcg_at_5": 0.24886, "ndcg_at_10": 0.20933, "ndcg_at_20": 0.2615, "ndcg_at_100": 0.3833, "ndcg_at_200": 0.42417, "ndcg_at_300": 0.43607, "ndcg_at_500": 0.44985, "ndcg_at_1000": 0.45848, "map_at_1": 0.03692, "map_at_3": 0.06538, "map_at_5": 0.08446, "map_at_10": 0.11207, "map_at_20": 0.13364, "map_at_100": 0.16637, "map_at_200": 0.17317, "map_at_300": 0.17435, "map_at_500": 0.17539, "map_at_1000": 0.17584, "recall_at_1": 0.03692, "recall_at_3": 0.07692, "recall_at_5": 0.11077, "recall_at_10": 0.17846, "recall_at_20": 0.27231, "recall_at_100": 0.58308, "recall_at_200": 0.71538, "recall_at_300": 0.75846, "recall_at_500": 0.81231, "recall_at_1000": 0.84923, "precision_at_1": 0.36923, "precision_at_3": 0.25641, "precision_at_5": 0.22154, "precision_at_10": 0.17846, "precision_at_20": 0.13615, "precision_at_100": 0.05831, "precision_at_200": 0.03577, "precision_at_300": 0.02528, "precision_at_500": 0.01625, "precision_at_1000": 0.00849, "mrr_at_1": 0.36923, "mrr_at_3": 0.43846, "mrr_at_5": 0.45462, "mrr_at_10": 0.4777, "mrr_at_20": 0.48492, "mrr_at_100": 0.4875, "mrr_at_200": 0.4876, "mrr_at_300": 0.4876, "mrr_at_500": 0.4876, "mrr_at_1000": 0.4876, "rc_at_1": {"relevant": 0.36923, "distractor": 0.56923}, "rc_at_3": {"relevant": 0.76923, "distractor": 2.09231}, "rc_at_5": {"relevant": 1.10769, "distractor": 3.64615}, "rc_at_10": {"relevant": 1.78462, "distractor": 7.41538}, "rc_at_20": {"relevant": 2.72308, "distractor": 14.87692}, "rc_at_100": {"relevant": 5.83077, "distractor": 55.58462}, "rc_at_200": {"relevant": 7.15385, "distractor": 68.32308}, "rc_at_300": {"relevant": 7.58462, "distractor": 73.67692}, "rc_at_500": {"relevant": 8.12308, "distractor": 78.35385}, "rc_at_1000": {"relevant": 8.49231, "distractor": 83.49231}}