{"ndcg_at_1": 0.36923, "ndcg_at_3": 0.34035, "ndcg_at_5": 0.28864, "ndcg_at_10": 0.228, "ndcg_at_20": 0.29011, "ndcg_at_100": 0.46536, "ndcg_at_200": 0.50795, "ndcg_at_300": 0.51603, "ndcg_at_500": 0.52316, "ndcg_at_1000": 0.52746, "map_at_1": 0.03692, "map_at_3": 0.08333, "map_at_5": 0.10279, "map_at_10": 0.12958, "map_at_20": 0.15911, "map_at_100": 0.21363, "map_at_200": 0.22155, "map_at_300": 0.22265, "map_at_500": 0.22327, "map_at_1000": 0.22347, "recall_at_1": 0.03692, "recall_at_3": 0.09846, "recall_at_5": 0.12923, "recall_at_10": 0.18615, "recall_at_20": 0.29846, "recall_at_100": 0.74154, "recall_at_200": 0.87692, "recall_at_300": 0.90615, "recall_at_500": 0.93385, "recall_at_1000": 0.95231, "precision_at_1": 0.36923, "precision_at_3": 0.32821, "precision_at_5": 0.25846, "precision_at_10": 0.18615, "precision_at_20": 0.14923, "precision_at_100": 0.07415, "precision_at_200": 0.04385, "precision_at_300": 0.03021, "precision_at_500": 0.01868, "precision_at_1000": 0.00952, "mrr_at_1": 0.36923, "mrr_at_3": 0.47436, "mrr_at_5": 0.48359, "mrr_at_10": 0.49436, "mrr_at_20": 0.50568, "mrr_at_100": 0.50908, "mrr_at_200": 0.50908, "mrr_at_300": 0.50908, "mrr_at_500": 0.50908, "mrr_at_1000": 0.50908, "rc_at_1": {"relevant": 0.36923, "distractor": 0.61538}, "rc_at_3": {"relevant": 0.98462, "distractor": 1.96923}, "rc_at_5": {"relevant": 1.29231, "distractor": 3.63077}, "rc_at_10": {"relevant": 1.86154, "distractor": 7.93846}, "rc_at_20": {"relevant": 2.98462, "distractor": 16.38462}, "rc_at_100": {"relevant": 7.41538, "distractor": 75.03077}, "rc_at_200": {"relevant": 8.76923, "distractor": 87.46154}, "rc_at_300": {"relevant": 9.06154, "distractor": 89.89231}, "rc_at_500": {"relevant": 9.33846, "distractor": 92.64615}, "rc_at_1000": {"relevant": 9.52308, "distractor": 94.69231}}