{"ndcg_at_1": 0.07587, "ndcg_at_3": 0.09235, "ndcg_at_5": 0.09766, "ndcg_at_10": 0.1108, "ndcg_at_20": 0.12091, "ndcg_at_100": 0.15206, "ndcg_at_200": 0.16487, "ndcg_at_300": 0.17221, "ndcg_at_500": 0.18133, "ndcg_at_1000": 0.19343, "map_at_1": 0.06045, "map_at_3": 0.07997, "map_at_5": 0.08323, "map_at_10": 0.0885, "map_at_20": 0.09127, "map_at_100": 0.09535, "map_at_200": 0.09607, "map_at_300": 0.09634, "map_at_500": 0.09657, "map_at_1000": 0.09677, "recall_at_1": 0.06045, "recall_at_3": 0.10345, "recall_at_5": 0.11638, "recall_at_10": 0.15581, "recall_at_20": 0.19373, "recall_at_100": 0.35183, "recall_at_200": 0.43342, "recall_at_300": 0.48649, "recall_at_500": 0.55772, "recall_at_1000": 0.6594, "precision_at_1": 0.07587, "precision_at_3": 0.04561, "precision_at_5": 0.03209, "precision_at_10": 0.02139, "precision_at_20": 0.01325, "precision_at_100": 0.00502, "precision_at_200": 0.0032, "precision_at_300": 0.00241, "precision_at_500": 0.00167, "precision_at_1000": 0.00102, "mrr_at_1": 0.0796, "mrr_at_3": 0.10303, "mrr_at_5": 0.10825, "mrr_at_10": 0.11517, "mrr_at_20": 0.11763, "mrr_at_100": 0.12179, "mrr_at_200": 0.1224, "mrr_at_300": 0.12259, "mrr_at_500": 0.12276, "mrr_at_1000": 0.1229, "rc_at_1": {"relevant": 0.0, "distractor": 0.0}, "rc_at_3": {"relevant": 0.0, "distractor": 0.0}, "rc_at_5": {"relevant": 0.0, "distractor": 0.0}, "rc_at_10": {"relevant": 0.0, "distractor": 0.0}, "rc_at_20": {"relevant": 0.0, "distractor": 0.0}, "rc_at_100": {"relevant": 0.0, "distractor": 0.0}, "rc_at_200": {"relevant": 0.0, "distractor": 0.0}, "rc_at_300": {"relevant": 0.0, "distractor": 0.0}, "rc_at_500": {"relevant": 0.0, "distractor": 0.0}, "rc_at_1000": {"relevant": 0.0, "distractor": 0.0}}