{"ndcg_at_1": 0.7966, "ndcg_at_3": 0.84014, "ndcg_at_5": 0.85761, "ndcg_at_10": 0.87108, "ndcg_at_20": 0.87812, "ndcg_at_100": 0.88411, "ndcg_at_200": 0.88493, "ndcg_at_300": 0.88511, "ndcg_at_500": 0.88529, "ndcg_at_1000": 0.8854, "map_at_1": 0.69202, "map_at_3": 0.80122, "map_at_5": 0.82055, "map_at_10": 0.83159, "map_at_20": 0.83584, "map_at_100": 0.83806, "map_at_200": 0.8382, "map_at_300": 0.83822, "map_at_500": 0.83824, "map_at_1000": 0.83825, "recall_at_1": 0.69202, "recall_at_3": 0.85967, "recall_at_5": 0.90827, "recall_at_10": 0.94782, "recall_at_20": 0.97082, "recall_at_100": 0.99319, "recall_at_200": 0.99678, "recall_at_300": 0.99753, "recall_at_500": 0.9985, "recall_at_1000": 0.99919, "precision_at_1": 0.7966, "precision_at_3": 0.3674, "precision_at_5": 0.2427, "precision_at_10": 0.13272, "precision_at_20": 0.07053, "precision_at_100": 0.01521, "precision_at_200": 0.00773, "precision_at_300": 0.00518, "precision_at_500": 0.00312, "precision_at_1000": 0.00156, "mrr_at_1": 0.7966, "mrr_at_3": 0.85067, "mrr_at_5": 0.8583, "mrr_at_10": 0.8618, "mrr_at_20": 0.8627, "mrr_at_100": 0.86297, "mrr_at_200": 0.86298, "mrr_at_300": 0.86298, "mrr_at_500": 0.86298, "mrr_at_1000": 0.86298, "rc_at_1": {"relevant": 0.0, "distractor": 0.0}, "rc_at_3": {"relevant": 0.0, "distractor": 0.0}, "rc_at_5": {"relevant": 0.0, "distractor": 0.0}, "rc_at_10": {"relevant": 0.0, "distractor": 0.0}, "rc_at_20": {"relevant": 0.0, "distractor": 0.0}, "rc_at_100": {"relevant": 0.0, "distractor": 0.0}, "rc_at_200": {"relevant": 0.0, "distractor": 0.0}, "rc_at_300": {"relevant": 0.0, "distractor": 0.0}, "rc_at_500": {"relevant": 0.0, "distractor": 0.0}, "rc_at_1000": {"relevant": 0.0, "distractor": 0.0}}