{"ndcg_at_1": 0.46154, "ndcg_at_3": 0.38178, "ndcg_at_5": 0.33789, "ndcg_at_10": 0.27786, "ndcg_at_20": 0.32307, "ndcg_at_100": 0.50483, "ndcg_at_200": 0.55456, "ndcg_at_300": 0.55925, "ndcg_at_500": 0.56362, "ndcg_at_1000": 0.56686, "map_at_1": 0.04615, "map_at_3": 0.09744, "map_at_5": 0.12844, "map_at_10": 0.16727, "map_at_20": 0.18925, "map_at_100": 0.24376, "map_at_200": 0.25467, "map_at_300": 0.25523, "map_at_500": 0.25564, "map_at_1000": 0.25583, "recall_at_1": 0.04615, "recall_at_3": 0.10769, "recall_at_5": 0.15231, "recall_at_10": 0.23692, "recall_at_20": 0.31846, "recall_at_100": 0.78769, "recall_at_200": 0.94308, "recall_at_300": 0.96, "recall_at_500": 0.97692, "recall_at_1000": 0.99077, "precision_at_1": 0.46154, "precision_at_3": 0.35897, "precision_at_5": 0.30462, "precision_at_10": 0.23692, "precision_at_20": 0.15923, "precision_at_100": 0.07877, "precision_at_200": 0.04715, "precision_at_300": 0.032, "precision_at_500": 0.01954, "precision_at_1000": 0.00991, "mrr_at_1": 0.46154, "mrr_at_3": 0.52821, "mrr_at_5": 0.54205, "mrr_at_10": 0.5576, "mrr_at_20": 0.56449, "mrr_at_100": 0.56749, "mrr_at_200": 0.56749, "mrr_at_300": 0.56749, "mrr_at_500": 0.56749, "mrr_at_1000": 0.56749, "rc_at_1": {"relevant": 0.46154, "distractor": 0.53846}, "rc_at_3": {"relevant": 1.07692, "distractor": 1.92308}, "rc_at_5": {"relevant": 1.52308, "distractor": 3.47692}, "rc_at_10": {"relevant": 2.36923, "distractor": 7.58462}, "rc_at_20": {"relevant": 3.18462, "distractor": 16.66154}, "rc_at_100": {"relevant": 7.87692, "distractor": 86.21538}, "rc_at_200": {"relevant": 9.43077, "distractor": 96.87692}, "rc_at_300": {"relevant": 9.6, "distractor": 97.70769}, "rc_at_500": {"relevant": 9.76923, "distractor": 98.52308}, "rc_at_1000": {"relevant": 9.90769, "distractor": 99.12308}}