{"ndcg_at_1": 0.27055, "ndcg_at_3": 0.31426, "ndcg_at_5": 0.33799, "ndcg_at_10": 0.35896, "ndcg_at_20": 0.37864, "ndcg_at_100": 0.41668, "ndcg_at_200": 0.42582, "ndcg_at_300": 0.43109, "ndcg_at_500": 0.43619, "ndcg_at_1000": 0.44203, "map_at_1": 0.22208, "map_at_3": 0.28119, "map_at_5": 0.29797, "map_at_10": 0.30847, "map_at_20": 0.31477, "map_at_100": 0.3208, "map_at_200": 0.32146, "map_at_300": 0.32169, "map_at_500": 0.32183, "map_at_1000": 0.32195, "recall_at_1": 0.22208, "recall_at_3": 0.34008, "recall_at_5": 0.40044, "recall_at_10": 0.4644, "recall_at_20": 0.5354, "recall_at_100": 0.71962, "recall_at_200": 0.77523, "recall_at_300": 0.81236, "recall_at_500": 0.84896, "recall_at_1000": 0.89545, "precision_at_1": 0.27055, "precision_at_3": 0.1503, "precision_at_5": 0.10913, "precision_at_10": 0.06461, "precision_at_20": 0.03813, "precision_at_100": 0.01089, "precision_at_200": 0.00604, "precision_at_300": 0.00425, "precision_at_500": 0.00272, "precision_at_1000": 0.00146, "mrr_at_1": 0.26826, "mrr_at_3": 0.33257, "mrr_at_5": 0.34444, "mrr_at_10": 0.35292, "mrr_at_20": 0.35816, "mrr_at_100": 0.36252, "mrr_at_200": 0.36287, "mrr_at_300": 0.36298, "mrr_at_500": 0.36306, "mrr_at_1000": 0.36312, "rc_at_1": {"relevant": 0.0, "distractor": 0.0}, "rc_at_3": {"relevant": 0.0, "distractor": 0.0}, "rc_at_5": {"relevant": 0.0, "distractor": 0.0}, "rc_at_10": {"relevant": 0.0, "distractor": 0.0}, "rc_at_20": {"relevant": 0.0, "distractor": 0.0}, "rc_at_100": {"relevant": 0.0, "distractor": 0.0}, "rc_at_200": {"relevant": 0.0, "distractor": 0.0}, "rc_at_300": {"relevant": 0.0, "distractor": 0.0}, "rc_at_500": {"relevant": 0.0, "distractor": 0.0}, "rc_at_1000": {"relevant": 0.0, "distractor": 0.0}}