{"ndcg_at_1": 0.12608, "ndcg_at_3": 0.13954, "ndcg_at_5": 0.14997, "ndcg_at_10": 0.16273, "ndcg_at_20": 0.17731, "ndcg_at_100": 0.20705, "ndcg_at_200": 0.21635, "ndcg_at_300": 0.22283, "ndcg_at_500": 0.23205, "ndcg_at_1000": 0.24271, "map_at_1": 0.11065, "map_at_3": 0.12893, "map_at_5": 0.13501, "map_at_10": 0.14036, "map_at_20": 0.14464, "map_at_100": 0.14875, "map_at_200": 0.14928, "map_at_300": 0.14953, "map_at_500": 0.14977, "map_at_1000": 0.14994, "recall_at_1": 0.11065, "recall_at_3": 0.14932, "recall_at_5": 0.17488, "recall_at_10": 0.21387, "recall_at_20": 0.26596, "recall_at_100": 0.41094, "recall_at_200": 0.4695, "recall_at_300": 0.51461, "recall_at_500": 0.58582, "recall_at_1000": 0.67555, "precision_at_1": 0.12608, "precision_at_3": 0.05999, "precision_at_5": 0.04331, "precision_at_10": 0.02705, "precision_at_20": 0.01752, "precision_at_100": 0.00596, "precision_at_200": 0.0035, "precision_at_300": 0.00261, "precision_at_500": 0.0018, "precision_at_1000": 0.00106, "mrr_at_1": 0.12608, "mrr_at_3": 0.14581, "mrr_at_5": 0.15337, "mrr_at_10": 0.15959, "mrr_at_20": 0.16399, "mrr_at_100": 0.16825, "mrr_at_200": 0.1687, "mrr_at_300": 0.16887, "mrr_at_500": 0.16906, "mrr_at_1000": 0.16918, "rc_at_1": {"relevant": 0.0, "distractor": 0.0}, "rc_at_3": {"relevant": 0.0, "distractor": 0.0}, "rc_at_5": {"relevant": 0.0, "distractor": 0.0}, "rc_at_10": {"relevant": 0.0, "distractor": 0.0}, "rc_at_20": {"relevant": 0.0, "distractor": 0.0}, "rc_at_100": {"relevant": 0.0, "distractor": 0.0}, "rc_at_200": {"relevant": 0.0, "distractor": 0.0}, "rc_at_300": {"relevant": 0.0, "distractor": 0.0}, "rc_at_500": {"relevant": 0.0, "distractor": 0.0}, "rc_at_1000": {"relevant": 0.0, "distractor": 0.0}}