{"ndcg_at_1": 0.29, "ndcg_at_3": 0.24233, "ndcg_at_5": 0.21902, "ndcg_at_10": 0.20102, "ndcg_at_20": 0.19572, "ndcg_at_100": 0.21951, "ndcg_at_200": 0.2362, "ndcg_at_300": 0.24598, "ndcg_at_500": 0.25873, "ndcg_at_1000": 0.27634, "map_at_1": 0.03535, "map_at_3": 0.05413, "map_at_5": 0.06165, "map_at_10": 0.07056, "map_at_20": 0.07863, "map_at_100": 0.09052, "map_at_200": 0.09324, "map_at_300": 0.09444, "map_at_500": 0.09568, "map_at_1000": 0.09684, "recall_at_1": 0.03535, "recall_at_3": 0.06649, "recall_at_5": 0.08183, "recall_at_10": 0.10919, "recall_at_20": 0.14791, "recall_at_100": 0.24618, "recall_at_200": 0.29875, "recall_at_300": 0.32909, "recall_at_500": 0.37424, "recall_at_1000": 0.44095, "precision_at_1": 0.36, "precision_at_3": 0.26, "precision_at_5": 0.2095, "precision_at_10": 0.15125, "precision_at_20": 0.1125, "precision_at_100": 0.04725, "precision_at_200": 0.03086, "precision_at_300": 0.02382, "precision_at_500": 0.01718, "precision_at_1000": 0.01093, "mrr_at_1": 0.36, "mrr_at_3": 0.44625, "mrr_at_5": 0.45913, "mrr_at_10": 0.46581, "mrr_at_20": 0.47111, "mrr_at_100": 0.47437, "mrr_at_200": 0.47463, "mrr_at_300": 0.47468, "mrr_at_500": 0.47473, "mrr_at_1000": 0.47473, "rc_at_1": {"relevant": 0.0, "distractor": 0.0}, "rc_at_3": {"relevant": 0.0, "distractor": 0.0}, "rc_at_5": {"relevant": 0.0, "distractor": 0.0}, "rc_at_10": {"relevant": 0.0, "distractor": 0.0}, "rc_at_20": {"relevant": 0.0, "distractor": 0.0}, "rc_at_100": {"relevant": 0.0, "distractor": 0.0}, "rc_at_200": {"relevant": 0.0, "distractor": 0.0}, "rc_at_300": {"relevant": 0.0, "distractor": 0.0}, "rc_at_500": {"relevant": 0.0, "distractor": 0.0}, "rc_at_1000": {"relevant": 0.0, "distractor": 0.0}}