{"ndcg_at_1": 0.4, "ndcg_at_3": 0.35385, "ndcg_at_5": 0.31165, "ndcg_at_10": 0.25028, "ndcg_at_20": 0.30621, "ndcg_at_100": 0.43656, "ndcg_at_200": 0.47575, "ndcg_at_300": 0.49071, "ndcg_at_500": 0.50223, "ndcg_at_1000": 0.51219, "map_at_1": 0.04, "map_at_3": 0.08615, "map_at_5": 0.11062, "map_at_10": 0.14002, "map_at_20": 0.16955, "map_at_100": 0.20942, "map_at_200": 0.21609, "map_at_300": 0.21773, "map_at_500": 0.21871, "map_at_1000": 0.21917, "recall_at_1": 0.04, "recall_at_3": 0.10154, "recall_at_5": 0.14154, "recall_at_10": 0.20923, "recall_at_20": 0.30923, "recall_at_100": 0.63538, "recall_at_200": 0.76154, "recall_at_300": 0.81538, "recall_at_500": 0.86, "recall_at_1000": 0.90308, "precision_at_1": 0.4, "precision_at_3": 0.33846, "precision_at_5": 0.28308, "precision_at_10": 0.20923, "precision_at_20": 0.15462, "precision_at_100": 0.06354, "precision_at_200": 0.03808, "precision_at_300": 0.02718, "precision_at_500": 0.0172, "precision_at_1000": 0.00903, "mrr_at_1": 0.4, "mrr_at_3": 0.49744, "mrr_at_5": 0.51128, "mrr_at_10": 0.52587, "mrr_at_20": 0.53276, "mrr_at_100": 0.53481, "mrr_at_200": 0.53481, "mrr_at_300": 0.53481, "mrr_at_500": 0.53481, "mrr_at_1000": 0.53481, "rc_at_1": {"relevant": 0.4, "distractor": 0.6}, "rc_at_3": {"relevant": 1.01538, "distractor": 1.95385}, "rc_at_5": {"relevant": 1.41538, "distractor": 3.50769}, "rc_at_10": {"relevant": 2.09231, "distractor": 7.58462}, "rc_at_20": {"relevant": 3.09231, "distractor": 15.36923}, "rc_at_100": {"relevant": 6.35385, "distractor": 60.18462}, "rc_at_200": {"relevant": 7.61538, "distractor": 75.2}, "rc_at_300": {"relevant": 8.15385, "distractor": 80.33846}, "rc_at_500": {"relevant": 8.6, "distractor": 85.16923}, "rc_at_1000": {"relevant": 9.03077, "distractor": 89.41538}}