{"ndcg_at_1": 0.36364, "ndcg_at_3": 0.30686, "ndcg_at_5": 0.26449, "ndcg_at_10": 0.21834, "ndcg_at_20": 0.27745, "ndcg_at_100": 0.37267, "ndcg_at_200": 0.38561, "ndcg_at_300": 0.39773, "ndcg_at_500": 0.40605, "ndcg_at_1000": 0.41529, "map_at_1": 0.03636, "map_at_3": 0.07576, "map_at_5": 0.09439, "map_at_10": 0.11573, "map_at_20": 0.14348, "map_at_100": 0.17374, "map_at_200": 0.1757, "map_at_300": 0.17683, "map_at_500": 0.1773, "map_at_1000": 0.17772, "recall_at_1": 0.03636, "recall_at_3": 0.08727, "recall_at_5": 0.11818, "recall_at_10": 0.18545, "recall_at_20": 0.29273, "recall_at_100": 0.52727, "recall_at_200": 0.56909, "recall_at_300": 0.61273, "recall_at_500": 0.64545, "recall_at_1000": 0.68545, "precision_at_1": 0.36364, "precision_at_3": 0.29091, "precision_at_5": 0.23636, "precision_at_10": 0.18545, "precision_at_20": 0.14636, "precision_at_100": 0.05273, "precision_at_200": 0.02845, "precision_at_300": 0.02042, "precision_at_500": 0.01291, "precision_at_1000": 0.00685, "mrr_at_1": 0.36364, "mrr_at_3": 0.43636, "mrr_at_5": 0.45273, "mrr_at_10": 0.47997, "mrr_at_20": 0.48379, "mrr_at_100": 0.4848, "mrr_at_200": 0.48496, "mrr_at_300": 0.48496, "mrr_at_500": 0.485, "mrr_at_1000": 0.48503, "rc_at_1": {"relevant": 0.36364, "distractor": 0.54545}, "rc_at_3": {"relevant": 0.87273, "distractor": 1.89091}, "rc_at_5": {"relevant": 1.18182, "distractor": 3.23636}, "rc_at_10": {"relevant": 1.87273, "distractor": 6.38182}, "rc_at_20": {"relevant": 2.92727, "distractor": 11.76364}, "rc_at_100": {"relevant": 5.27273, "distractor": 35.18182}, "rc_at_200": {"relevant": 5.67273, "distractor": 44.01818}, "rc_at_300": {"relevant": 6.12727, "distractor": 48.32727}, "rc_at_500": {"relevant": 6.45455, "distractor": 53.90909}, "rc_at_1000": {"relevant": 6.85455, "distractor": 60.92727}}