{"ndcg_at_1": 0.6366, "ndcg_at_3": 0.50289, "ndcg_at_5": 0.52511, "ndcg_at_10": 0.54811, "ndcg_at_20": 0.56278, "ndcg_at_100": 0.58289, "ndcg_at_200": 0.58882, "ndcg_at_300": 0.59172, "ndcg_at_500": 0.59517, "ndcg_at_1000": 0.59925, "map_at_1": 0.3183, "map_at_3": 0.42996, "map_at_5": 0.44596, "map_at_10": 0.45857, "map_at_20": 0.46406, "map_at_100": 0.46786, "map_at_200": 0.46829, "map_at_300": 0.46843, "map_at_500": 0.46854, "map_at_1000": 0.46863, "recall_at_1": 0.3183, "recall_at_3": 0.47333, "recall_at_5": 0.51722, "recall_at_10": 0.57488, "recall_at_20": 0.62201, "recall_at_100": 0.71067, "recall_at_200": 0.74531, "recall_at_300": 0.76408, "recall_at_500": 0.78825, "recall_at_1000": 0.81965, "precision_at_1": 0.6366, "precision_at_3": 0.31555, "precision_at_5": 0.20689, "precision_at_10": 0.11498, "precision_at_20": 0.0622, "precision_at_100": 0.01421, "precision_at_200": 0.00745, "precision_at_300": 0.00509, "precision_at_500": 0.00315, "precision_at_1000": 0.00164, "mrr_at_1": 0.6366, "mrr_at_3": 0.69269, "mrr_at_5": 0.70099, "mrr_at_10": 0.70697, "mrr_at_20": 0.70924, "mrr_at_100": 0.71065, "mrr_at_200": 0.71078, "mrr_at_300": 0.71082, "mrr_at_500": 0.71084, "mrr_at_1000": 0.71085, "rc_at_1": {"relevant": 0.0, "distractor": 0.0}, "rc_at_3": {"relevant": 0.0, "distractor": 0.0}, "rc_at_5": {"relevant": 0.0, "distractor": 0.0}, "rc_at_10": {"relevant": 0.0, "distractor": 0.0}, "rc_at_20": {"relevant": 0.0, "distractor": 0.0}, "rc_at_100": {"relevant": 0.0, "distractor": 0.0}, "rc_at_200": {"relevant": 0.0, "distractor": 0.0}, "rc_at_300": {"relevant": 0.0, "distractor": 0.0}, "rc_at_500": {"relevant": 0.0, "distractor": 0.0}, "rc_at_1000": {"relevant": 0.0, "distractor": 0.0}}