{"ndcg_at_1": 0.06154, "ndcg_at_3": 0.08698, "ndcg_at_5": 0.07566, "ndcg_at_10": 0.06225, "ndcg_at_20": 0.08635, "ndcg_at_100": 0.13728, "ndcg_at_200": 0.16247, "ndcg_at_300": 0.17319, "ndcg_at_500": 0.18967, "ndcg_at_1000": 0.21662, "map_at_1": 0.00615, "map_at_3": 0.01538, "map_at_5": 0.01854, "map_at_10": 0.02287, "map_at_20": 0.02971, "map_at_100": 0.03882, "map_at_200": 0.04112, "map_at_300": 0.04194, "map_at_500": 0.04264, "map_at_1000": 0.04358, "recall_at_1": 0.00615, "recall_at_3": 0.02769, "recall_at_5": 0.03692, "recall_at_10": 0.05538, "recall_at_20": 0.09846, "recall_at_100": 0.22615, "recall_at_200": 0.30769, "recall_at_300": 0.34615, "recall_at_500": 0.41077, "recall_at_1000": 0.52615, "precision_at_1": 0.06154, "precision_at_3": 0.09231, "precision_at_5": 0.07385, "precision_at_10": 0.05538, "precision_at_20": 0.04923, "precision_at_100": 0.02262, "precision_at_200": 0.01538, "precision_at_300": 0.01154, "precision_at_500": 0.00822, "precision_at_1000": 0.00526, "mrr_at_1": 0.06154, "mrr_at_3": 0.15385, "mrr_at_5": 0.16385, "mrr_at_10": 0.17154, "mrr_at_20": 0.18231, "mrr_at_100": 0.18822, "mrr_at_200": 0.18917, "mrr_at_300": 0.18934, "mrr_at_500": 0.18942, "mrr_at_1000": 0.18943, "rc_at_1": {"relevant": 0.06154, "distractor": 0.58462}, "rc_at_3": {"relevant": 0.27692, "distractor": 1.47692}, "rc_at_5": {"relevant": 0.36923, "distractor": 2.27692}, "rc_at_10": {"relevant": 0.55385, "distractor": 4.12308}, "rc_at_20": {"relevant": 0.96923, "distractor": 7.33846}, "rc_at_100": {"relevant": 2.26154, "distractor": 22.46154}, "rc_at_200": {"relevant": 3.07692, "distractor": 30.89231}, "rc_at_300": {"relevant": 3.47692, "distractor": 36.06154}, "rc_at_500": {"relevant": 4.10769, "distractor": 43.01538}, "rc_at_1000": {"relevant": 5.26154, "distractor": 53.23077}}