{"ndcg_at_1": 0.42994, "ndcg_at_3": 0.46912, "ndcg_at_5": 0.48886, "ndcg_at_10": 0.50973, "ndcg_at_20": 0.52613, "ndcg_at_100": 0.55018, "ndcg_at_200": 0.55769, "ndcg_at_300": 0.5611, "ndcg_at_500": 0.56459, "ndcg_at_1000": 0.56774, "map_at_1": 0.34143, "map_at_3": 0.41891, "map_at_5": 0.43746, "map_at_10": 0.45062, "map_at_20": 0.45785, "map_at_100": 0.46371, "map_at_200": 0.46449, "map_at_300": 0.46472, "map_at_500": 0.46488, "map_at_1000": 0.46496, "recall_at_1": 0.34143, "recall_at_3": 0.48281, "recall_at_5": 0.54213, "recall_at_10": 0.60841, "recall_at_20": 0.66746, "recall_at_100": 0.77924, "recall_at_200": 0.82104, "recall_at_300": 0.84215, "recall_at_500": 0.86544, "recall_at_1000": 0.8881, "precision_at_1": 0.42994, "precision_at_3": 0.2276, "precision_at_5": 0.15949, "precision_at_10": 0.0958, "precision_at_20": 0.05659, "precision_at_100": 0.01505, "precision_at_200": 0.00828, "precision_at_300": 0.00577, "precision_at_500": 0.00363, "precision_at_1000": 0.00191, "mrr_at_1": 0.42994, "mrr_at_3": 0.49268, "mrr_at_5": 0.50564, "mrr_at_10": 0.51435, "mrr_at_20": 0.51787, "mrr_at_100": 0.52011, "mrr_at_200": 0.52034, "mrr_at_300": 0.52041, "mrr_at_500": 0.52046, "mrr_at_1000": 0.52048, "rc_at_1": {"relevant": 0.0, "distractor": 0.0}, "rc_at_3": {"relevant": 0.0, "distractor": 0.0}, "rc_at_5": {"relevant": 0.0, "distractor": 0.0}, "rc_at_10": {"relevant": 0.0, "distractor": 0.0}, "rc_at_20": {"relevant": 0.0, "distractor": 0.0}, "rc_at_100": {"relevant": 0.0, "distractor": 0.0}, "rc_at_200": {"relevant": 0.0, "distractor": 0.0}, "rc_at_300": {"relevant": 0.0, "distractor": 0.0}, "rc_at_500": {"relevant": 0.0, "distractor": 0.0}, "rc_at_1000": {"relevant": 0.0, "distractor": 0.0}}