{"ndcg_at_1": 0.27045, "ndcg_at_3": 0.30177, "ndcg_at_5": 0.32035, "ndcg_at_10": 0.3433, "ndcg_at_20": 0.35848, "ndcg_at_100": 0.39324, "ndcg_at_200": 0.40655, "ndcg_at_300": 0.41143, "ndcg_at_500": 0.41698, "ndcg_at_1000": 0.42298, "map_at_1": 0.22541, "map_at_3": 0.27319, "map_at_5": 0.28543, "map_at_10": 0.29658, "map_at_20": 0.30122, "map_at_100": 0.30662, "map_at_200": 0.30753, "map_at_300": 0.30775, "map_at_500": 0.30793, "map_at_1000": 0.30805, "recall_at_1": 0.22541, "recall_at_3": 0.32315, "recall_at_5": 0.37112, "recall_at_10": 0.43837, "recall_at_20": 0.49268, "recall_at_100": 0.65819, "recall_at_200": 0.73968, "recall_at_300": 0.77201, "recall_at_500": 0.81234, "recall_at_1000": 0.86174, "precision_at_1": 0.27045, "precision_at_3": 0.13795, "precision_at_5": 0.09759, "precision_at_10": 0.06054, "precision_at_20": 0.03494, "precision_at_100": 0.01013, "precision_at_200": 0.00589, "precision_at_300": 0.00419, "precision_at_500": 0.00269, "precision_at_1000": 0.00144, "mrr_at_1": 0.27045, "mrr_at_3": 0.32114, "mrr_at_5": 0.33322, "mrr_at_10": 0.34291, "mrr_at_20": 0.34734, "mrr_at_100": 0.35136, "mrr_at_200": 0.35186, "mrr_at_300": 0.35196, "mrr_at_500": 0.35205, "mrr_at_1000": 0.35211, "rc_at_1": {"relevant": 0.0, "distractor": 0.0}, "rc_at_3": {"relevant": 0.0, "distractor": 0.0}, "rc_at_5": {"relevant": 0.0, "distractor": 0.0}, "rc_at_10": {"relevant": 0.0, "distractor": 0.0}, "rc_at_20": {"relevant": 0.0, "distractor": 0.0}, "rc_at_100": {"relevant": 0.0, "distractor": 0.0}, "rc_at_200": {"relevant": 0.0, "distractor": 0.0}, "rc_at_300": {"relevant": 0.0, "distractor": 0.0}, "rc_at_500": {"relevant": 0.0, "distractor": 0.0}, "rc_at_1000": {"relevant": 0.0, "distractor": 0.0}}