{"ndcg_at_1": 0.21066, "ndcg_at_3": 0.24122, "ndcg_at_5": 0.25471, "ndcg_at_10": 0.27291, "ndcg_at_20": 0.28782, "ndcg_at_100": 0.31358, "ndcg_at_200": 0.32272, "ndcg_at_300": 0.32836, "ndcg_at_500": 0.33401, "ndcg_at_1000": 0.34133, "map_at_1": 0.18506, "map_at_3": 0.22307, "map_at_5": 0.23162, "map_at_10": 0.23969, "map_at_20": 0.24419, "map_at_100": 0.24809, "map_at_200": 0.24862, "map_at_300": 0.24883, "map_at_500": 0.24899, "map_at_1000": 0.2491, "recall_at_1": 0.18506, "recall_at_3": 0.26447, "recall_at_5": 0.29733, "recall_at_10": 0.35015, "recall_at_20": 0.40516, "recall_at_100": 0.53337, "recall_at_200": 0.59386, "recall_at_300": 0.63544, "recall_at_500": 0.67994, "recall_at_1000": 0.74443, "precision_at_1": 0.21066, "precision_at_3": 0.10533, "precision_at_5": 0.0721, "precision_at_10": 0.04395, "precision_at_20": 0.02618, "precision_at_100": 0.00719, "precision_at_200": 0.00403, "precision_at_300": 0.00288, "precision_at_500": 0.00186, "precision_at_1000": 0.00102, "mrr_at_1": 0.21066, "mrr_at_3": 0.24869, "mrr_at_5": 0.25628, "mrr_at_10": 0.26366, "mrr_at_20": 0.26799, "mrr_at_100": 0.27123, "mrr_at_200": 0.27166, "mrr_at_300": 0.27183, "mrr_at_500": 0.27193, "mrr_at_1000": 0.27202, "rc_at_1": {"relevant": 0.0, "distractor": 0.0}, "rc_at_3": {"relevant": 0.0, "distractor": 0.0}, "rc_at_5": {"relevant": 0.0, "distractor": 0.0}, "rc_at_10": {"relevant": 0.0, "distractor": 0.0}, "rc_at_20": {"relevant": 0.0, "distractor": 0.0}, "rc_at_100": {"relevant": 0.0, "distractor": 0.0}, "rc_at_200": {"relevant": 0.0, "distractor": 0.0}, "rc_at_300": {"relevant": 0.0, "distractor": 0.0}, "rc_at_500": {"relevant": 0.0, "distractor": 0.0}, "rc_at_1000": {"relevant": 0.0, "distractor": 0.0}}