{"ndcg_at_1": 0.46154, "ndcg_at_3": 0.37172, "ndcg_at_5": 0.3131, "ndcg_at_10": 0.26587, "ndcg_at_20": 0.3089, "ndcg_at_100": 0.4995, "ndcg_at_200": 0.54357, "ndcg_at_300": 0.54701, "ndcg_at_500": 0.55019, "ndcg_at_1000": 0.55232, "map_at_1": 0.04615, "map_at_3": 0.09231, "map_at_5": 0.112, "map_at_10": 0.15204, "map_at_20": 0.17649, "map_at_100": 0.23074, "map_at_200": 0.2402, "map_at_300": 0.24068, "map_at_500": 0.24097, "map_at_1000": 0.24108, "recall_at_1": 0.04615, "recall_at_3": 0.10462, "recall_at_5": 0.13692, "recall_at_10": 0.22615, "recall_at_20": 0.30462, "recall_at_100": 0.79846, "recall_at_200": 0.93692, "recall_at_300": 0.94923, "recall_at_500": 0.96154, "recall_at_1000": 0.97077, "precision_at_1": 0.46154, "precision_at_3": 0.34872, "precision_at_5": 0.27385, "precision_at_10": 0.22615, "precision_at_20": 0.15231, "precision_at_100": 0.07985, "precision_at_200": 0.04685, "precision_at_300": 0.03164, "precision_at_500": 0.01923, "precision_at_1000": 0.00971, "mrr_at_1": 0.46154, "mrr_at_3": 0.53333, "mrr_at_5": 0.54026, "mrr_at_10": 0.56284, "mrr_at_20": 0.568, "mrr_at_100": 0.57101, "mrr_at_200": 0.57101, "mrr_at_300": 0.57101, "mrr_at_500": 0.57101, "mrr_at_1000": 0.57101, "rc_at_1": {"relevant": 0.46154, "distractor": 0.53846}, "rc_at_3": {"relevant": 1.04615, "distractor": 1.92308}, "rc_at_5": {"relevant": 1.36923, "distractor": 3.58462}, "rc_at_10": {"relevant": 2.26154, "distractor": 7.64615}, "rc_at_20": {"relevant": 3.04615, "distractor": 16.70769}, "rc_at_100": {"relevant": 7.98462, "distractor": 82.61538}, "rc_at_200": {"relevant": 9.36923, "distractor": 94.64615}, "rc_at_300": {"relevant": 9.49231, "distractor": 96.0}, "rc_at_500": {"relevant": 9.61538, "distractor": 97.23077}, "rc_at_1000": {"relevant": 9.70769, "distractor": 97.96923}}