{"ndcg_at_1": 0.10117, "ndcg_at_3": 0.13167, "ndcg_at_5": 0.14737, "ndcg_at_10": 0.16653, "ndcg_at_20": 0.18434, "ndcg_at_100": 0.2206, "ndcg_at_200": 0.23264, "ndcg_at_300": 0.23988, "ndcg_at_500": 0.248, "ndcg_at_1000": 0.25838, "map_at_1": 0.08296, "map_at_3": 0.11377, "map_at_5": 0.12341, "map_at_10": 0.13168, "map_at_20": 0.13688, "map_at_100": 0.14208, "map_at_200": 0.14283, "map_at_300": 0.14312, "map_at_500": 0.14336, "map_at_1000": 0.14355, "recall_at_1": 0.08296, "recall_at_3": 0.15139, "recall_at_5": 0.19206, "recall_at_10": 0.24888, "recall_at_20": 0.31467, "recall_at_100": 0.49708, "recall_at_200": 0.57304, "recall_at_300": 0.62389, "recall_at_500": 0.68624, "recall_at_1000": 0.77309, "precision_at_1": 0.10117, "precision_at_3": 0.06469, "precision_at_5": 0.04914, "precision_at_10": 0.03297, "precision_at_20": 0.02149, "precision_at_100": 0.0073, "precision_at_200": 0.00437, "precision_at_300": 0.00323, "precision_at_500": 0.00217, "precision_at_1000": 0.00125, "mrr_at_1": 0.10083, "mrr_at_3": 0.13633, "mrr_at_5": 0.14684, "mrr_at_10": 0.15588, "mrr_at_20": 0.16104, "mrr_at_100": 0.16558, "mrr_at_200": 0.16613, "mrr_at_300": 0.16632, "mrr_at_500": 0.16647, "mrr_at_1000": 0.16658, "rc_at_1": {"relevant": 0.0, "distractor": 0.0}, "rc_at_3": {"relevant": 0.0, "distractor": 0.0}, "rc_at_5": {"relevant": 0.0, "distractor": 0.0}, "rc_at_10": {"relevant": 0.0, "distractor": 0.0}, "rc_at_20": {"relevant": 0.0, "distractor": 0.0}, "rc_at_100": {"relevant": 0.0, "distractor": 0.0}, "rc_at_200": {"relevant": 0.0, "distractor": 0.0}, "rc_at_300": {"relevant": 0.0, "distractor": 0.0}, "rc_at_500": {"relevant": 0.0, "distractor": 0.0}, "rc_at_1000": {"relevant": 0.0, "distractor": 0.0}}