{"ndcg_at_1": 0.43827, "ndcg_at_3": 0.40493, "ndcg_at_5": 0.41433, "ndcg_at_10": 0.43939, "ndcg_at_20": 0.46794, "ndcg_at_100": 0.5081, "ndcg_at_200": 0.5194, "ndcg_at_300": 0.52421, "ndcg_at_500": 0.53063, "ndcg_at_1000": 0.53621, "map_at_1": 0.22426, "map_at_3": 0.31767, "map_at_5": 0.34179, "map_at_10": 0.36113, "map_at_20": 0.37274, "map_at_100": 0.38183, "map_at_200": 0.38282, "map_at_300": 0.38308, "map_at_500": 0.38334, "map_at_1000": 0.38349, "recall_at_1": 0.22426, "recall_at_3": 0.36377, "recall_at_5": 0.42441, "recall_at_10": 0.50536, "recall_at_20": 0.59039, "recall_at_100": 0.7505, "recall_at_200": 0.81057, "recall_at_300": 0.83965, "recall_at_500": 0.8825, "recall_at_1000": 0.92202, "precision_at_1": 0.43827, "precision_at_3": 0.268, "precision_at_5": 0.19506, "precision_at_10": 0.12052, "precision_at_20": 0.07292, "precision_at_100": 0.01932, "precision_at_200": 0.01053, "precision_at_300": 0.00728, "precision_at_500": 0.0046, "precision_at_1000": 0.00241, "mrr_at_1": 0.43827, "mrr_at_3": 0.49691, "mrr_at_5": 0.51042, "mrr_at_10": 0.52086, "mrr_at_20": 0.52604, "mrr_at_100": 0.52856, "mrr_at_200": 0.52884, "mrr_at_300": 0.52892, "mrr_at_500": 0.52898, "mrr_at_1000": 0.529, "rc_at_1": {"relevant": 0.0, "distractor": 0.0}, "rc_at_3": {"relevant": 0.0, "distractor": 0.0}, "rc_at_5": {"relevant": 0.0, "distractor": 0.0}, "rc_at_10": {"relevant": 0.0, "distractor": 0.0}, "rc_at_20": {"relevant": 0.0, "distractor": 0.0}, "rc_at_100": {"relevant": 0.0, "distractor": 0.0}, "rc_at_200": {"relevant": 0.0, "distractor": 0.0}, "rc_at_300": {"relevant": 0.0, "distractor": 0.0}, "rc_at_500": {"relevant": 0.0, "distractor": 0.0}, "rc_at_1000": {"relevant": 0.0, "distractor": 0.0}}