{"ndcg_at_1": 0.04068, "ndcg_at_3": 0.05958, "ndcg_at_5": 0.07142, "ndcg_at_10": 0.08091, "ndcg_at_20": 0.09315, "ndcg_at_100": 0.12027, "ndcg_at_200": 0.12868, "ndcg_at_300": 0.13558, "ndcg_at_500": 0.14347, "ndcg_at_1000": 0.15399, "map_at_1": 0.0355, "map_at_3": 0.05255, "map_at_5": 0.05923, "map_at_10": 0.06341, "map_at_20": 0.06673, "map_at_100": 0.07021, "map_at_200": 0.07066, "map_at_300": 0.07089, "map_at_500": 0.07107, "map_at_1000": 0.07122, "recall_at_1": 0.0355, "recall_at_3": 0.07213, "recall_at_5": 0.10095, "recall_at_10": 0.12901, "recall_at_20": 0.17628, "recall_at_100": 0.32199, "recall_at_200": 0.37945, "recall_at_300": 0.43223, "recall_at_500": 0.49802, "recall_at_1000": 0.59156, "precision_at_1": 0.04068, "precision_at_3": 0.02825, "precision_at_5": 0.0235, "precision_at_10": 0.01503, "precision_at_20": 0.01017, "precision_at_100": 0.00375, "precision_at_200": 0.00221, "precision_at_300": 0.00168, "precision_at_500": 0.00116, "precision_at_1000": 0.00071, "mrr_at_1": 0.05085, "mrr_at_3": 0.06591, "mrr_at_5": 0.07286, "mrr_at_10": 0.07779, "mrr_at_20": 0.08084, "mrr_at_100": 0.08418, "mrr_at_200": 0.08478, "mrr_at_300": 0.08495, "mrr_at_500": 0.08514, "mrr_at_1000": 0.08526, "rc_at_1": {"relevant": 0.0, "distractor": 0.0}, "rc_at_3": {"relevant": 0.0, "distractor": 0.0}, "rc_at_5": {"relevant": 0.0, "distractor": 0.0}, "rc_at_10": {"relevant": 0.0, "distractor": 0.0}, "rc_at_20": {"relevant": 0.0, "distractor": 0.0}, "rc_at_100": {"relevant": 0.0, "distractor": 0.0}, "rc_at_200": {"relevant": 0.0, "distractor": 0.0}, "rc_at_300": {"relevant": 0.0, "distractor": 0.0}, "rc_at_500": {"relevant": 0.0, "distractor": 0.0}, "rc_at_1000": {"relevant": 0.0, "distractor": 0.0}}