{"ndcg_at_1": 0.73396, "ndcg_at_3": 0.57458, "ndcg_at_5": 0.59706, "ndcg_at_10": 0.61528, "ndcg_at_20": 0.62807, "ndcg_at_100": 0.64508, "ndcg_at_200": 0.65006, "ndcg_at_300": 0.65259, "ndcg_at_500": 0.65522, "ndcg_at_1000": 0.65898, "map_at_1": 0.36698, "map_at_3": 0.49884, "map_at_5": 0.51585, "map_at_10": 0.52613, "map_at_20": 0.53112, "map_at_100": 0.53448, "map_at_200": 0.53485, "map_at_300": 0.53498, "map_at_500": 0.53507, "map_at_1000": 0.53514, "recall_at_1": 0.36698, "recall_at_3": 0.53666, "recall_at_5": 0.58096, "recall_at_10": 0.6266, "recall_at_20": 0.66779, "recall_at_100": 0.74294, "recall_at_200": 0.77191, "recall_at_300": 0.78832, "recall_at_500": 0.80675, "recall_at_1000": 0.83572, "precision_at_1": 0.73396, "precision_at_3": 0.35778, "precision_at_5": 0.23238, "precision_at_10": 0.12532, "precision_at_20": 0.06678, "precision_at_100": 0.01486, "precision_at_200": 0.00772, "precision_at_300": 0.00526, "precision_at_500": 0.00323, "precision_at_1000": 0.00167, "mrr_at_1": 0.73396, "mrr_at_3": 0.78166, "mrr_at_5": 0.78854, "mrr_at_10": 0.79272, "mrr_at_20": 0.79423, "mrr_at_100": 0.7951, "mrr_at_200": 0.79519, "mrr_at_300": 0.79521, "mrr_at_500": 0.79522, "mrr_at_1000": 0.79523, "rc_at_1": {"relevant": 0.0, "distractor": 0.0}, "rc_at_3": {"relevant": 0.0, "distractor": 0.0}, "rc_at_5": {"relevant": 0.0, "distractor": 0.0}, "rc_at_10": {"relevant": 0.0, "distractor": 0.0}, "rc_at_20": {"relevant": 0.0, "distractor": 0.0}, "rc_at_100": {"relevant": 0.0, "distractor": 0.0}, "rc_at_200": {"relevant": 0.0, "distractor": 0.0}, "rc_at_300": {"relevant": 0.0, "distractor": 0.0}, "rc_at_500": {"relevant": 0.0, "distractor": 0.0}, "rc_at_1000": {"relevant": 0.0, "distractor": 0.0}}