{"ndcg_at_1": 0.245, "ndcg_at_3": 0.19207, "ndcg_at_5": 0.16955, "ndcg_at_10": 0.20437, "ndcg_at_20": 0.23467, "ndcg_at_100": 0.28552, "ndcg_at_200": 0.30204, "ndcg_at_300": 0.31151, "ndcg_at_500": 0.32363, "ndcg_at_1000": 0.33864, "map_at_1": 0.04978, "map_at_3": 0.08629, "map_at_5": 0.10431, "map_at_10": 0.12201, "map_at_20": 0.1333, "map_at_100": 0.14319, "map_at_200": 0.14468, "map_at_300": 0.14526, "map_at_500": 0.14576, "map_at_1000": 0.14617, "recall_at_1": 0.04978, "recall_at_3": 0.10803, "recall_at_5": 0.15067, "recall_at_10": 0.21502, "recall_at_20": 0.28587, "recall_at_100": 0.4522, "recall_at_200": 0.52273, "recall_at_300": 0.5673, "recall_at_500": 0.62925, "recall_at_1000": 0.71345, "precision_at_1": 0.245, "precision_at_3": 0.17767, "precision_at_5": 0.1486, "precision_at_10": 0.106, "precision_at_20": 0.0705, "precision_at_100": 0.02228, "precision_at_200": 0.01286, "precision_at_300": 0.00931, "precision_at_500": 0.00619, "precision_at_1000": 0.00351, "mrr_at_1": 0.245, "mrr_at_3": 0.3155, "mrr_at_5": 0.33515, "mrr_at_10": 0.34898, "mrr_at_20": 0.35611, "mrr_at_100": 0.36023, "mrr_at_200": 0.36055, "mrr_at_300": 0.36064, "mrr_at_500": 0.36073, "mrr_at_1000": 0.36076, "rc_at_1": {"relevant": 0.0, "distractor": 0.0}, "rc_at_3": {"relevant": 0.0, "distractor": 0.0}, "rc_at_5": {"relevant": 0.0, "distractor": 0.0}, "rc_at_10": {"relevant": 0.0, "distractor": 0.0}, "rc_at_20": {"relevant": 0.0, "distractor": 0.0}, "rc_at_100": {"relevant": 0.0, "distractor": 0.0}, "rc_at_200": {"relevant": 0.0, "distractor": 0.0}, "rc_at_300": {"relevant": 0.0, "distractor": 0.0}, "rc_at_500": {"relevant": 0.0, "distractor": 0.0}, "rc_at_1000": {"relevant": 0.0, "distractor": 0.0}}